m3_xlwt/BIFFRecords.py
m3_xlwt/Bitmap.py
m3_xlwt/Cell.py
m3_xlwt/Column.py
m3_xlwt/CompoundDoc.py
m3_xlwt/ExcelFormula.py
m3_xlwt/ExcelFormulaLexer.py
m3_xlwt/ExcelFormulaParser.py
m3_xlwt/ExcelMagic.py
m3_xlwt/Formatting.py
m3_xlwt/Row.py
m3_xlwt/Style.py
m3_xlwt/UnicodeUtils.py
m3_xlwt/Utils.py
m3_xlwt/Workbook.py
m3_xlwt/Worksheet.py
m3_xlwt/__init__.py
m3_xlwt/antlr.py
m3_xlwt/compat.py
m3_xlwt/excel-formula.g
m3_xlwt-1.3.0.3.dist-info/LICENSE
m3_xlwt-1.3.0.3.dist-info/METADATA
m3_xlwt-1.3.0.3.dist-info/WHEEL
m3_xlwt-1.3.0.3.dist-info/top_level.txt
m3_xlwt-1.3.0.3.dist-info/RECORD
