Metadata-Version: 2.1
Name: m3-xlwt
Version: 1.3.0.3
Summary: Патч официальной библиотеки xlwt для работы с excel-файлами
Home-page: https://stash.bars-open.ru/projects/M3/repos/m3-xlwt/browse
Author: BARS Group
Author-email: a.danilenko@bars.group
License: Apache License, Version 2.0
Classifier: Intended Audience :: Developers
Classifier: Environment :: Web Environment
Classifier: Natural Language :: Russian
Classifier: Natural Language :: English
Classifier: Operating System :: OS Independent
Classifier: Programming Language :: Python
License-File: LICENSE
